{
  "origin": "codeshovel",
  "repositoryName": "checkstyle",
  "repositoryPath": "/home/ncbradley/codeshovel-repos/checkstyle/.git",
  "startCommitName": "119fd4fb33bef9f5c66fc950396669af842c21a3",
  "sourceFileName": "VisibilityModifierCheck.java",
  "functionName": "beginTree",
  "functionId": "beginTree___rootAst-DetailAST",
  "sourceFilePath": "src/main/java/com/puppycrawl/tools/checkstyle/checks/design/VisibilityModifierCheck.java",
  "functionStartLine": 419,
  "functionEndLine": 429,
  "changeHistory": [
    "5f68bb50fd191fec409f5edb90755a18fce3e0ac",
    "f9f60d3142533c3eebff775e8eb1159935faaba1"
  ],
  "changeHistoryShort": {
    "5f68bb50fd191fec409f5edb90755a18fce3e0ac": "Ybodychange",
    "f9f60d3142533c3eebff775e8eb1159935faaba1": "Yintroduced"
  },
  "changeHistoryDetails": {
    "5f68bb50fd191fec409f5edb90755a18fce3e0ac": {
      "type": "Ybodychange",
      "commitMessage": "Visibility Modifier Check, ignore annotated fields\n",
      "commitDate": 1425777291000,
      "commitName": "5f68bb50fd191fec409f5edb90755a18fce3e0ac",
      "commitAuthor": "alexkravin",
      "commitDateOld": 1425417238000,
      "commitNameOld": "de4485a22bfe8eafc3c2e273fd328a0221d0ff9e",
      "commitAuthorOld": "alexkravin",
      "daysBetweenCommits": 4.17,
      "commitsBetweenForRepo": 21,
      "commitsBetweenForFile": 1,
      "diff": "@@ -1,6 +1,12 @@\n     public void beginTree(DetailAST rootAst)\n     {\n         immutableClassShortNames.clear();\n-        final List\u003cString\u003e shortNames \u003d getClassShortNames(immutableClassCanonicalNames);\n-        immutableClassShortNames.addAll(shortNames);\n+        final List\u003cString\u003e classShortNames \u003d\n+                getClassShortNames(immutableClassCanonicalNames);\n+        immutableClassShortNames.addAll(classShortNames);\n+\n+        ignoreAnnotationShortNames.clear();\n+        final List\u003cString\u003e annotationShortNames \u003d\n+                getClassShortNames(ignoreAnnotationCanonicalNames);\n+        ignoreAnnotationShortNames.addAll(annotationShortNames);\n     }\n\\ No newline at end of file\n"
    },
    "f9f60d3142533c3eebff775e8eb1159935faaba1": {
      "type": "Yintroduced",
      "commitMessage": "Visibility Modifier Check, added option allows public immutable fields, issue #61\n",
      "commitDate": 1424982930000,
      "commitName": "f9f60d3142533c3eebff775e8eb1159935faaba1",
      "commitAuthor": "alexkravin"
    }
  }
}