{
  "origin": "codeshovel",
  "repositoryName": "commons-io",
  "repositoryPath": "/repos/commons-io/.git",
  "startCommitName": "559de2c461e94ab636c959149c775bb27111fb48",
  "sourceFileName": "FilenameUtils.java",
  "functionName": "concat",
  "functionId": "concat___basePath-String__fullFileNameToAdd-String",
  "sourceFilePath": "src/main/java/org/apache/commons/io/FilenameUtils.java",
  "functionStartLine": 491,
  "functionEndLine": 511,
  "changeHistory": [
    "d24dd1a3abc4624be55c0772ae4432686ee18792",
    "0f98e790a43b17ae1bb60d264931fb4f13300762",
    "6aa00766b9103d75c763160280429af8e1f0549e",
    "83f7246c3e9fe1d3f1ad6cf7ea0715a573fe2f2a",
    "f1d5bd46189049da24493a971e0e420a1345191c",
    "a09ebfc6c0f84a0aa9a05da04801461d99509ec5",
    "289a56cf5d5c89ad3d85389b9651b0e227ded057",
    "9628bca96999535c33adad8a0a3a5afa4c755340",
    "8d33a71d3c6ef9e1a55d7013841adb1614ec3c26",
    "d5e24a4f1a2ff0e5c565f5b78fc0691e639b876e",
    "b901739a6779843da45a917a141cfd17114909de",
    "8eeb52fc81c4e65c00839cfeef9f1cde8b1cc613",
    "c360a10db25701f682849e5913d150f13a09f3bb"
  ],
  "changeHistoryShort": {
    "d24dd1a3abc4624be55c0772ae4432686ee18792": "Ymultichange(Yparameterchange,Ybodychange)",
    "0f98e790a43b17ae1bb60d264931fb4f13300762": "Ybodychange",
    "6aa00766b9103d75c763160280429af8e1f0549e": "Ymultichange(Ybodychange,Yparametermetachange)",
    "83f7246c3e9fe1d3f1ad6cf7ea0715a573fe2f2a": "Yfilerename",
    "f1d5bd46189049da24493a971e0e420a1345191c": "Ybodychange",
    "a09ebfc6c0f84a0aa9a05da04801461d99509ec5": "Ymultichange(Yparameterchange,Ybodychange)",
    "289a56cf5d5c89ad3d85389b9651b0e227ded057": "Ymultichange(Yrename,Yparameterchange,Ybodychange)",
    "9628bca96999535c33adad8a0a3a5afa4c755340": "Ybodychange",
    "8d33a71d3c6ef9e1a55d7013841adb1614ec3c26": "Ybodychange",
    "d5e24a4f1a2ff0e5c565f5b78fc0691e639b876e": "Yparametermetachange",
    "b901739a6779843da45a917a141cfd17114909de": "Ymovefromfile",
    "8eeb52fc81c4e65c00839cfeef9f1cde8b1cc613": "Ymovefromfile",
    "c360a10db25701f682849e5913d150f13a09f3bb": "Yintroduced"
  },
  "changeHistoryDetails": {
    "d24dd1a3abc4624be55c0772ae4432686ee18792": {
      "type": "Ymultichange(Yparameterchange,Ybodychange)",
      "commitMessage": "Fix param names \u0027*Filename*\u0027 -\u003e \u0027*FileName*\u0027 in code and Javadocs.",
      "commitDate": 1520524295000,
      "commitName": "d24dd1a3abc4624be55c0772ae4432686ee18792",
      "commitAuthor": "Gary Gregory",
      "subchanges": [
        {
          "type": "Yparameterchange",
          "commitMessage": "Fix param names \u0027*Filename*\u0027 -\u003e \u0027*FileName*\u0027 in code and Javadocs.",
          "commitDate": 1520524295000,
          "commitName": "d24dd1a3abc4624be55c0772ae4432686ee18792",
          "commitAuthor": "Gary Gregory",
          "commitDateOld": 1520524225000,
          "commitNameOld": "e4e03ef4c091f5a35da0d97a6a35224197b8be02",
          "commitAuthorOld": "Gary Gregory",
          "daysBetweenCommits": 0.0,
          "commitsBetweenForRepo": 1,
          "commitsBetweenForFile": 1,
          "diff": "@@ -1,21 +1,21 @@\n-    public static String concat(final String basePath, final String fullFilenameToAdd) {\n-        final int prefix \u003d getPrefixLength(fullFilenameToAdd);\n+    public static String concat(final String basePath, final String fullFileNameToAdd) {\n+        final int prefix \u003d getPrefixLength(fullFileNameToAdd);\n         if (prefix \u003c 0) {\n             return null;\n         }\n         if (prefix \u003e 0) {\n-            return normalize(fullFilenameToAdd);\n+            return normalize(fullFileNameToAdd);\n         }\n         if (basePath \u003d\u003d null) {\n             return null;\n         }\n         final int len \u003d basePath.length();\n         if (len \u003d\u003d 0) {\n-            return normalize(fullFilenameToAdd);\n+            return normalize(fullFileNameToAdd);\n         }\n         final char ch \u003d basePath.charAt(len - 1);\n         if (isSeparator(ch)) {\n-            return normalize(basePath + fullFilenameToAdd);\n+            return normalize(basePath + fullFileNameToAdd);\n         }\n-        return normalize(basePath + \u0027/\u0027 + fullFilenameToAdd);\n+        return normalize(basePath + \u0027/\u0027 + fullFileNameToAdd);\n     }\n\\ No newline at end of file\n",
          "extendedDetails": {}
        },
        {
          "type": "Ybodychange",
          "commitMessage": "Fix param names \u0027*Filename*\u0027 -\u003e \u0027*FileName*\u0027 in code and Javadocs.",
          "commitDate": 1520524295000,
          "commitName": "d24dd1a3abc4624be55c0772ae4432686ee18792",
          "commitAuthor": "Gary Gregory",
          "commitDateOld": 1520524225000,
          "commitNameOld": "e4e03ef4c091f5a35da0d97a6a35224197b8be02",
          "commitAuthorOld": "Gary Gregory",
          "daysBetweenCommits": 0.0,
          "commitsBetweenForRepo": 1,
          "commitsBetweenForFile": 1,
          "diff": "@@ -1,21 +1,21 @@\n-    public static String concat(final String basePath, final String fullFilenameToAdd) {\n-        final int prefix \u003d getPrefixLength(fullFilenameToAdd);\n+    public static String concat(final String basePath, final String fullFileNameToAdd) {\n+        final int prefix \u003d getPrefixLength(fullFileNameToAdd);\n         if (prefix \u003c 0) {\n             return null;\n         }\n         if (prefix \u003e 0) {\n-            return normalize(fullFilenameToAdd);\n+            return normalize(fullFileNameToAdd);\n         }\n         if (basePath \u003d\u003d null) {\n             return null;\n         }\n         final int len \u003d basePath.length();\n         if (len \u003d\u003d 0) {\n-            return normalize(fullFilenameToAdd);\n+            return normalize(fullFileNameToAdd);\n         }\n         final char ch \u003d basePath.charAt(len - 1);\n         if (isSeparator(ch)) {\n-            return normalize(basePath + fullFilenameToAdd);\n+            return normalize(basePath + fullFileNameToAdd);\n         }\n-        return normalize(basePath + \u0027/\u0027 + fullFilenameToAdd);\n+        return normalize(basePath + \u0027/\u0027 + fullFileNameToAdd);\n     }\n\\ No newline at end of file\n",
          "extendedDetails": {}
        }
      ]
    },
    "0f98e790a43b17ae1bb60d264931fb4f13300762": {
      "type": "Ybodychange",
      "commitMessage": "Don\u0027t need to nest else clause.",
      "commitDate": 1520354728000,
      "commitName": "0f98e790a43b17ae1bb60d264931fb4f13300762",
      "commitAuthor": "Gary Gregory",
      "commitDateOld": 1520354618000,
      "commitNameOld": "a653a4487774f57a7aff2c9dc1fe40b9b221cb6b",
      "commitAuthorOld": "Gary Gregory",
      "daysBetweenCommits": 0.0,
      "commitsBetweenForRepo": 1,
      "commitsBetweenForFile": 1,
      "diff": "@@ -1,22 +1,21 @@\n     public static String concat(final String basePath, final String fullFilenameToAdd) {\n         final int prefix \u003d getPrefixLength(fullFilenameToAdd);\n         if (prefix \u003c 0) {\n             return null;\n         }\n         if (prefix \u003e 0) {\n             return normalize(fullFilenameToAdd);\n         }\n         if (basePath \u003d\u003d null) {\n             return null;\n         }\n         final int len \u003d basePath.length();\n         if (len \u003d\u003d 0) {\n             return normalize(fullFilenameToAdd);\n         }\n         final char ch \u003d basePath.charAt(len - 1);\n         if (isSeparator(ch)) {\n             return normalize(basePath + fullFilenameToAdd);\n-        } else {\n-            return normalize(basePath + \u0027/\u0027 + fullFilenameToAdd);\n         }\n+        return normalize(basePath + \u0027/\u0027 + fullFilenameToAdd);\n     }\n\\ No newline at end of file\n",
      "extendedDetails": {}
    },
    "6aa00766b9103d75c763160280429af8e1f0549e": {
      "type": "Ymultichange(Ybodychange,Yparametermetachange)",
      "commitMessage": "Use final where possible.\n\ngit-svn-id: https://svn.apache.org/repos/asf/commons/proper/io/trunk@1415850 13f79535-47bb-0310-9956-ffa450edef68\n",
      "commitDate": 1354308699000,
      "commitName": "6aa00766b9103d75c763160280429af8e1f0549e",
      "commitAuthor": "Gary D. Gregory",
      "subchanges": [
        {
          "type": "Ybodychange",
          "commitMessage": "Use final where possible.\n\ngit-svn-id: https://svn.apache.org/repos/asf/commons/proper/io/trunk@1415850 13f79535-47bb-0310-9956-ffa450edef68\n",
          "commitDate": 1354308699000,
          "commitName": "6aa00766b9103d75c763160280429af8e1f0549e",
          "commitAuthor": "Gary D. Gregory",
          "commitDateOld": 1333120391000,
          "commitNameOld": "3ef56378e33ed5ccc296806e4ad6b8c463e5979f",
          "commitAuthorOld": "Gary D. Gregory",
          "daysBetweenCommits": 245.24,
          "commitsBetweenForRepo": 143,
          "commitsBetweenForFile": 1,
          "diff": "@@ -1,22 +1,22 @@\n-    public static String concat(String basePath, String fullFilenameToAdd) {\n-        int prefix \u003d getPrefixLength(fullFilenameToAdd);\n+    public static String concat(final String basePath, final String fullFilenameToAdd) {\n+        final int prefix \u003d getPrefixLength(fullFilenameToAdd);\n         if (prefix \u003c 0) {\n             return null;\n         }\n         if (prefix \u003e 0) {\n             return normalize(fullFilenameToAdd);\n         }\n         if (basePath \u003d\u003d null) {\n             return null;\n         }\n-        int len \u003d basePath.length();\n+        final int len \u003d basePath.length();\n         if (len \u003d\u003d 0) {\n             return normalize(fullFilenameToAdd);\n         }\n-        char ch \u003d basePath.charAt(len - 1);\n+        final char ch \u003d basePath.charAt(len - 1);\n         if (isSeparator(ch)) {\n             return normalize(basePath + fullFilenameToAdd);\n         } else {\n             return normalize(basePath + \u0027/\u0027 + fullFilenameToAdd);\n         }\n     }\n\\ No newline at end of file\n",
          "extendedDetails": {}
        },
        {
          "type": "Yparametermetachange",
          "commitMessage": "Use final where possible.\n\ngit-svn-id: https://svn.apache.org/repos/asf/commons/proper/io/trunk@1415850 13f79535-47bb-0310-9956-ffa450edef68\n",
          "commitDate": 1354308699000,
          "commitName": "6aa00766b9103d75c763160280429af8e1f0549e",
          "commitAuthor": "Gary D. Gregory",
          "commitDateOld": 1333120391000,
          "commitNameOld": "3ef56378e33ed5ccc296806e4ad6b8c463e5979f",
          "commitAuthorOld": "Gary D. Gregory",
          "daysBetweenCommits": 245.24,
          "commitsBetweenForRepo": 143,
          "commitsBetweenForFile": 1,
          "diff": "@@ -1,22 +1,22 @@\n-    public static String concat(String basePath, String fullFilenameToAdd) {\n-        int prefix \u003d getPrefixLength(fullFilenameToAdd);\n+    public static String concat(final String basePath, final String fullFilenameToAdd) {\n+        final int prefix \u003d getPrefixLength(fullFilenameToAdd);\n         if (prefix \u003c 0) {\n             return null;\n         }\n         if (prefix \u003e 0) {\n             return normalize(fullFilenameToAdd);\n         }\n         if (basePath \u003d\u003d null) {\n             return null;\n         }\n-        int len \u003d basePath.length();\n+        final int len \u003d basePath.length();\n         if (len \u003d\u003d 0) {\n             return normalize(fullFilenameToAdd);\n         }\n-        char ch \u003d basePath.charAt(len - 1);\n+        final char ch \u003d basePath.charAt(len - 1);\n         if (isSeparator(ch)) {\n             return normalize(basePath + fullFilenameToAdd);\n         } else {\n             return normalize(basePath + \u0027/\u0027 + fullFilenameToAdd);\n         }\n     }\n\\ No newline at end of file\n",
          "extendedDetails": {}
        }
      ]
    },
    "83f7246c3e9fe1d3f1ad6cf7ea0715a573fe2f2a": {
      "type": "Yfilerename",
      "commitMessage": "Build changes - re-organize to standard m2 layout, remove useless JIRA report and fix some Ant issues\n\ngit-svn-id: https://svn.apache.org/repos/asf/commons/proper/io/trunk@1004358 13f79535-47bb-0310-9956-ffa450edef68\n",
      "commitDate": 1286218476000,
      "commitName": "83f7246c3e9fe1d3f1ad6cf7ea0715a573fe2f2a",
      "commitAuthor": "Niall Pemberton",
      "commitDateOld": 1286214840000,
      "commitNameOld": "19f48eb1711427a43a5e10c84bbbf1218a08bdd2",
      "commitAuthorOld": "Niall Pemberton",
      "daysBetweenCommits": 0.04,
      "commitsBetweenForRepo": 1,
      "commitsBetweenForFile": 1,
      "diff": "",
      "extendedDetails": {
        "oldPath": "src/java/org/apache/commons/io/FilenameUtils.java",
        "newPath": "src/main/java/org/apache/commons/io/FilenameUtils.java"
      }
    },
    "f1d5bd46189049da24493a971e0e420a1345191c": {
      "type": "Ybodychange",
      "commitMessage": "Fix a little style problem.\n\ngit-svn-id: https://svn.apache.org/repos/asf/jakarta/commons/proper/io/trunk@201611 13f79535-47bb-0310-9956-ffa450edef68\n",
      "commitDate": 1119618304000,
      "commitName": "f1d5bd46189049da24493a971e0e420a1345191c",
      "commitAuthor": "Jeremias Maerki",
      "commitDateOld": 1112830543000,
      "commitNameOld": "745375d22e427574f1ef1301c8378cd81e85a1fc",
      "commitAuthorOld": "Stephen Colebourne",
      "daysBetweenCommits": 78.56,
      "commitsBetweenForRepo": 4,
      "commitsBetweenForFile": 1,
      "diff": "@@ -1,22 +1,22 @@\n     public static String concat(String basePath, String fullFilenameToAdd) {\n         int prefix \u003d getPrefixLength(fullFilenameToAdd);\n         if (prefix \u003c 0) {\n             return null;\n         }\n         if (prefix \u003e 0) {\n             return normalize(fullFilenameToAdd);\n         }\n         if (basePath \u003d\u003d null) {\n             return null;\n         }\n         int len \u003d basePath.length();\n         if (len \u003d\u003d 0) {\n             return normalize(fullFilenameToAdd);\n         }\n         char ch \u003d basePath.charAt(len - 1);\n-        if (isSeparator(basePath.charAt(len - 1))) {\n+        if (isSeparator(ch)) {\n             return normalize(basePath + fullFilenameToAdd);\n         } else {\n             return normalize(basePath + \u0027/\u0027 + fullFilenameToAdd);\n         }\n     }\n\\ No newline at end of file\n",
      "extendedDetails": {}
    },
    "a09ebfc6c0f84a0aa9a05da04801461d99509ec5": {
      "type": "Ymultichange(Yparameterchange,Ybodychange)",
      "commitMessage": "Add equals methods, document Unix/Windows behaviour\n\n\ngit-svn-id: https://svn.apache.org/repos/asf/jakarta/commons/proper/io/trunk@140646 13f79535-47bb-0310-9956-ffa450edef68\n",
      "commitDate": 1102188520000,
      "commitName": "a09ebfc6c0f84a0aa9a05da04801461d99509ec5",
      "commitAuthor": "Stephen Colebourne",
      "subchanges": [
        {
          "type": "Yparameterchange",
          "commitMessage": "Add equals methods, document Unix/Windows behaviour\n\n\ngit-svn-id: https://svn.apache.org/repos/asf/jakarta/commons/proper/io/trunk@140646 13f79535-47bb-0310-9956-ffa450edef68\n",
          "commitDate": 1102188520000,
          "commitName": "a09ebfc6c0f84a0aa9a05da04801461d99509ec5",
          "commitAuthor": "Stephen Colebourne",
          "commitDateOld": 1101574851000,
          "commitNameOld": "289a56cf5d5c89ad3d85389b9651b0e227ded057",
          "commitAuthorOld": "Stephen Colebourne",
          "daysBetweenCommits": 7.1,
          "commitsBetweenForRepo": 1,
          "commitsBetweenForFile": 1,
          "diff": "@@ -1,22 +1,22 @@\n-    public static String concat(String basePath, String pathToAdd) {\n-        int prefix \u003d getPrefixLength(pathToAdd);\n+    public static String concat(String basePath, String fullFilenameToAdd) {\n+        int prefix \u003d getPrefixLength(fullFilenameToAdd);\n         if (prefix \u003c 0) {\n             return null;\n         }\n         if (prefix \u003e 0) {\n-            return normalize(pathToAdd);\n+            return normalize(fullFilenameToAdd);\n         }\n         if (basePath \u003d\u003d null) {\n             return null;\n         }\n         int len \u003d basePath.length();\n         if (len \u003d\u003d 0) {\n-            return normalize(pathToAdd);\n+            return normalize(fullFilenameToAdd);\n         }\n         char ch \u003d basePath.charAt(len - 1);\n         if (isSeparator(basePath.charAt(len - 1))) {\n-            return normalize(basePath + pathToAdd);\n+            return normalize(basePath + fullFilenameToAdd);\n         } else {\n-            return normalize(basePath + \u0027/\u0027 + pathToAdd);\n+            return normalize(basePath + \u0027/\u0027 + fullFilenameToAdd);\n         }\n     }\n\\ No newline at end of file\n",
          "extendedDetails": {}
        },
        {
          "type": "Ybodychange",
          "commitMessage": "Add equals methods, document Unix/Windows behaviour\n\n\ngit-svn-id: https://svn.apache.org/repos/asf/jakarta/commons/proper/io/trunk@140646 13f79535-47bb-0310-9956-ffa450edef68\n",
          "commitDate": 1102188520000,
          "commitName": "a09ebfc6c0f84a0aa9a05da04801461d99509ec5",
          "commitAuthor": "Stephen Colebourne",
          "commitDateOld": 1101574851000,
          "commitNameOld": "289a56cf5d5c89ad3d85389b9651b0e227ded057",
          "commitAuthorOld": "Stephen Colebourne",
          "daysBetweenCommits": 7.1,
          "commitsBetweenForRepo": 1,
          "commitsBetweenForFile": 1,
          "diff": "@@ -1,22 +1,22 @@\n-    public static String concat(String basePath, String pathToAdd) {\n-        int prefix \u003d getPrefixLength(pathToAdd);\n+    public static String concat(String basePath, String fullFilenameToAdd) {\n+        int prefix \u003d getPrefixLength(fullFilenameToAdd);\n         if (prefix \u003c 0) {\n             return null;\n         }\n         if (prefix \u003e 0) {\n-            return normalize(pathToAdd);\n+            return normalize(fullFilenameToAdd);\n         }\n         if (basePath \u003d\u003d null) {\n             return null;\n         }\n         int len \u003d basePath.length();\n         if (len \u003d\u003d 0) {\n-            return normalize(pathToAdd);\n+            return normalize(fullFilenameToAdd);\n         }\n         char ch \u003d basePath.charAt(len - 1);\n         if (isSeparator(basePath.charAt(len - 1))) {\n-            return normalize(basePath + pathToAdd);\n+            return normalize(basePath + fullFilenameToAdd);\n         } else {\n-            return normalize(basePath + \u0027/\u0027 + pathToAdd);\n+            return normalize(basePath + \u0027/\u0027 + fullFilenameToAdd);\n         }\n     }\n\\ No newline at end of file\n",
          "extendedDetails": {}
        }
      ]
    },
    "289a56cf5d5c89ad3d85389b9651b0e227ded057": {
      "type": "Ymultichange(Yrename,Yparameterchange,Ybodychange)",
      "commitMessage": "Rewrite catPath, renaming to concat\n\n\ngit-svn-id: https://svn.apache.org/repos/asf/jakarta/commons/proper/io/trunk@140645 13f79535-47bb-0310-9956-ffa450edef68\n",
      "commitDate": 1101574851000,
      "commitName": "289a56cf5d5c89ad3d85389b9651b0e227ded057",
      "commitAuthor": "Stephen Colebourne",
      "subchanges": [
        {
          "type": "Yrename",
          "commitMessage": "Rewrite catPath, renaming to concat\n\n\ngit-svn-id: https://svn.apache.org/repos/asf/jakarta/commons/proper/io/trunk@140645 13f79535-47bb-0310-9956-ffa450edef68\n",
          "commitDate": 1101574851000,
          "commitName": "289a56cf5d5c89ad3d85389b9651b0e227ded057",
          "commitAuthor": "Stephen Colebourne",
          "commitDateOld": 1101518525000,
          "commitNameOld": "3323d0a8d6167f47aac9b30c36979cd4daf610c8",
          "commitAuthorOld": "Stephen Colebourne",
          "daysBetweenCommits": 0.65,
          "commitsBetweenForRepo": 1,
          "commitsBetweenForFile": 1,
          "diff": "@@ -1,22 +1,22 @@\n-    public static String catPath(String lookupPath, String path) {\n-        // Cut off the last slash and everything beyond\n-        int index \u003d indexOfLastSeparator(lookupPath);\n-        String lookup \u003d lookupPath.substring(0, index);\n-        String pth \u003d path;\n-\n-        // Deal with .. by chopping dirs off the lookup path\n-        while (pth.startsWith(\"../\") || pth.startsWith(\"..\\\\\")) {\n-            if (lookup.length() \u003e 0) {\n-                index \u003d indexOfLastSeparator(lookup);\n-                lookup \u003d lookup.substring(0, index);\n-            } else {\n-                // More ..\u0027s than dirs, return null\n-                return null;\n-            }\n-\n-            pth \u003d pth.substring(3);\n+    public static String concat(String basePath, String pathToAdd) {\n+        int prefix \u003d getPrefixLength(pathToAdd);\n+        if (prefix \u003c 0) {\n+            return null;\n         }\n-\n-        return new StringBuffer(lookup).\n-                append(File.separator).append(pth).toString();\n+        if (prefix \u003e 0) {\n+            return normalize(pathToAdd);\n+        }\n+        if (basePath \u003d\u003d null) {\n+            return null;\n+        }\n+        int len \u003d basePath.length();\n+        if (len \u003d\u003d 0) {\n+            return normalize(pathToAdd);\n+        }\n+        char ch \u003d basePath.charAt(len - 1);\n+        if (isSeparator(basePath.charAt(len - 1))) {\n+            return normalize(basePath + pathToAdd);\n+        } else {\n+            return normalize(basePath + \u0027/\u0027 + pathToAdd);\n+        }\n     }\n\\ No newline at end of file\n",
          "extendedDetails": {
            "oldMethodName": "catPath",
            "newMethodName": "concat"
          }
        },
        {
          "type": "Yparameterchange",
          "commitMessage": "Rewrite catPath, renaming to concat\n\n\ngit-svn-id: https://svn.apache.org/repos/asf/jakarta/commons/proper/io/trunk@140645 13f79535-47bb-0310-9956-ffa450edef68\n",
          "commitDate": 1101574851000,
          "commitName": "289a56cf5d5c89ad3d85389b9651b0e227ded057",
          "commitAuthor": "Stephen Colebourne",
          "commitDateOld": 1101518525000,
          "commitNameOld": "3323d0a8d6167f47aac9b30c36979cd4daf610c8",
          "commitAuthorOld": "Stephen Colebourne",
          "daysBetweenCommits": 0.65,
          "commitsBetweenForRepo": 1,
          "commitsBetweenForFile": 1,
          "diff": "@@ -1,22 +1,22 @@\n-    public static String catPath(String lookupPath, String path) {\n-        // Cut off the last slash and everything beyond\n-        int index \u003d indexOfLastSeparator(lookupPath);\n-        String lookup \u003d lookupPath.substring(0, index);\n-        String pth \u003d path;\n-\n-        // Deal with .. by chopping dirs off the lookup path\n-        while (pth.startsWith(\"../\") || pth.startsWith(\"..\\\\\")) {\n-            if (lookup.length() \u003e 0) {\n-                index \u003d indexOfLastSeparator(lookup);\n-                lookup \u003d lookup.substring(0, index);\n-            } else {\n-                // More ..\u0027s than dirs, return null\n-                return null;\n-            }\n-\n-            pth \u003d pth.substring(3);\n+    public static String concat(String basePath, String pathToAdd) {\n+        int prefix \u003d getPrefixLength(pathToAdd);\n+        if (prefix \u003c 0) {\n+            return null;\n         }\n-\n-        return new StringBuffer(lookup).\n-                append(File.separator).append(pth).toString();\n+        if (prefix \u003e 0) {\n+            return normalize(pathToAdd);\n+        }\n+        if (basePath \u003d\u003d null) {\n+            return null;\n+        }\n+        int len \u003d basePath.length();\n+        if (len \u003d\u003d 0) {\n+            return normalize(pathToAdd);\n+        }\n+        char ch \u003d basePath.charAt(len - 1);\n+        if (isSeparator(basePath.charAt(len - 1))) {\n+            return normalize(basePath + pathToAdd);\n+        } else {\n+            return normalize(basePath + \u0027/\u0027 + pathToAdd);\n+        }\n     }\n\\ No newline at end of file\n",
          "extendedDetails": {}
        },
        {
          "type": "Ybodychange",
          "commitMessage": "Rewrite catPath, renaming to concat\n\n\ngit-svn-id: https://svn.apache.org/repos/asf/jakarta/commons/proper/io/trunk@140645 13f79535-47bb-0310-9956-ffa450edef68\n",
          "commitDate": 1101574851000,
          "commitName": "289a56cf5d5c89ad3d85389b9651b0e227ded057",
          "commitAuthor": "Stephen Colebourne",
          "commitDateOld": 1101518525000,
          "commitNameOld": "3323d0a8d6167f47aac9b30c36979cd4daf610c8",
          "commitAuthorOld": "Stephen Colebourne",
          "daysBetweenCommits": 0.65,
          "commitsBetweenForRepo": 1,
          "commitsBetweenForFile": 1,
          "diff": "@@ -1,22 +1,22 @@\n-    public static String catPath(String lookupPath, String path) {\n-        // Cut off the last slash and everything beyond\n-        int index \u003d indexOfLastSeparator(lookupPath);\n-        String lookup \u003d lookupPath.substring(0, index);\n-        String pth \u003d path;\n-\n-        // Deal with .. by chopping dirs off the lookup path\n-        while (pth.startsWith(\"../\") || pth.startsWith(\"..\\\\\")) {\n-            if (lookup.length() \u003e 0) {\n-                index \u003d indexOfLastSeparator(lookup);\n-                lookup \u003d lookup.substring(0, index);\n-            } else {\n-                // More ..\u0027s than dirs, return null\n-                return null;\n-            }\n-\n-            pth \u003d pth.substring(3);\n+    public static String concat(String basePath, String pathToAdd) {\n+        int prefix \u003d getPrefixLength(pathToAdd);\n+        if (prefix \u003c 0) {\n+            return null;\n         }\n-\n-        return new StringBuffer(lookup).\n-                append(File.separator).append(pth).toString();\n+        if (prefix \u003e 0) {\n+            return normalize(pathToAdd);\n+        }\n+        if (basePath \u003d\u003d null) {\n+            return null;\n+        }\n+        int len \u003d basePath.length();\n+        if (len \u003d\u003d 0) {\n+            return normalize(pathToAdd);\n+        }\n+        char ch \u003d basePath.charAt(len - 1);\n+        if (isSeparator(basePath.charAt(len - 1))) {\n+            return normalize(basePath + pathToAdd);\n+        } else {\n+            return normalize(basePath + \u0027/\u0027 + pathToAdd);\n+        }\n     }\n\\ No newline at end of file\n",
          "extendedDetails": {}
        }
      ]
    },
    "9628bca96999535c33adad8a0a3a5afa4c755340": {
      "type": "Ybodychange",
      "commitMessage": "Add indexOfXxx methods to FilenameUtils\n\n\ngit-svn-id: https://svn.apache.org/repos/asf/jakarta/commons/proper/io/trunk@140633 13f79535-47bb-0310-9956-ffa450edef68\n",
      "commitDate": 1099176117000,
      "commitName": "9628bca96999535c33adad8a0a3a5afa4c755340",
      "commitAuthor": "Stephen Colebourne",
      "commitDateOld": 1099174583000,
      "commitNameOld": "68f11e15de3b70c84c440fd861c69a3a5f15d644",
      "commitAuthorOld": "Stephen Colebourne",
      "daysBetweenCommits": 0.02,
      "commitsBetweenForRepo": 1,
      "commitsBetweenForFile": 1,
      "diff": "@@ -1,22 +1,22 @@\n     public static String catPath(String lookupPath, String path) {\n         // Cut off the last slash and everything beyond\n-        int index \u003d indexOfLastPathSeparator(lookupPath);\n+        int index \u003d indexOfLastSeparator(lookupPath);\n         String lookup \u003d lookupPath.substring(0, index);\n         String pth \u003d path;\n \n         // Deal with .. by chopping dirs off the lookup path\n         while (pth.startsWith(\"../\") || pth.startsWith(\"..\\\\\")) {\n             if (lookup.length() \u003e 0) {\n-                index \u003d indexOfLastPathSeparator(lookup);\n+                index \u003d indexOfLastSeparator(lookup);\n                 lookup \u003d lookup.substring(0, index);\n             } else {\n                 // More ..\u0027s than dirs, return null\n                 return null;\n             }\n \n             pth \u003d pth.substring(3);\n         }\n \n         return new StringBuffer(lookup).\n                 append(File.separator).append(pth).toString();\n     }\n\\ No newline at end of file\n",
      "extendedDetails": {}
    },
    "8d33a71d3c6ef9e1a55d7013841adb1614ec3c26": {
      "type": "Ybodychange",
      "commitMessage": "Bugzilla #27612\nFix for catPath not handling Windows-style path separators.\nSubmitted by: Maarten Coene \u003cMaarten.Coene.at.qmedit.com\u003e\n\n\ngit-svn-id: https://svn.apache.org/repos/asf/jakarta/commons/proper/io/trunk@140541 13f79535-47bb-0310-9956-ffa450edef68\n",
      "commitDate": 1079128759000,
      "commitName": "8d33a71d3c6ef9e1a55d7013841adb1614ec3c26",
      "commitAuthor": "Jeremias Maerki",
      "commitDateOld": 1077511229000,
      "commitNameOld": "ae5478f721fef2e41f248c6e85298714c8f6c445",
      "commitAuthorOld": "Henri Yandell",
      "daysBetweenCommits": 18.72,
      "commitsBetweenForRepo": 24,
      "commitsBetweenForFile": 1,
      "diff": "@@ -1,22 +1,21 @@\n     public static String catPath( String lookupPath, String path) {\n         // Cut off the last slash and everything beyond\n-        int index \u003d lookupPath.lastIndexOf(\"/\");\n+        int index \u003d indexOfLastPathSeparator(lookupPath);\n         String lookup \u003d lookupPath.substring(0, index);\n         String pth \u003d path;\n \n         // Deal with .. by chopping dirs off the lookup path\n-        while (pth.startsWith(\"../\")) {\n+        while (pth.startsWith(\"../\") || pth.startsWith(\"..\\\\\")) {\n             if (lookup.length() \u003e 0) {\n-                index \u003d lookup.lastIndexOf(\"/\");\n+                index \u003d indexOfLastPathSeparator(lookup);\n                 lookup \u003d lookup.substring(0, index);\n             } else {\n                 // More ..\u0027s than dirs, return null\n                 return null;\n             }\n \n-            index \u003d pth.indexOf(\"../\") + 3;\n-            pth \u003d pth.substring(index);\n+            pth \u003d pth.substring(3);\n         }\n \n-        return new StringBuffer(lookup).append(\"/\").append(pth).toString();\n+        return new StringBuffer(lookup).append(File.separator).append(pth).toString();\n     }\n\\ No newline at end of file\n",
      "extendedDetails": {}
    },
    "d5e24a4f1a2ff0e5c565f5b78fc0691e639b876e": {
      "type": "Yparametermetachange",
      "commitMessage": "removed lots of finals\n\n\ngit-svn-id: https://svn.apache.org/repos/asf/jakarta/commons/proper/io/trunk@140456 13f79535-47bb-0310-9956-ffa450edef68\n",
      "commitDate": 1072767169000,
      "commitName": "d5e24a4f1a2ff0e5c565f5b78fc0691e639b876e",
      "commitAuthor": "Henri Yandell",
      "commitDateOld": 1072677558000,
      "commitNameOld": "8baab07e0d47ba43a197933f6519141871fde6c3",
      "commitAuthorOld": "Henri Yandell",
      "daysBetweenCommits": 1.04,
      "commitsBetweenForRepo": 5,
      "commitsBetweenForFile": 1,
      "diff": "@@ -1,22 +1,22 @@\n-    public static String catPath(final String lookupPath, final String path) {\n+    public static String catPath( String lookupPath, String path) {\n         // Cut off the last slash and everything beyond\n         int index \u003d lookupPath.lastIndexOf(\"/\");\n         String lookup \u003d lookupPath.substring(0, index);\n         String pth \u003d path;\n \n         // Deal with .. by chopping dirs off the lookup path\n         while (pth.startsWith(\"../\")) {\n             if (lookup.length() \u003e 0) {\n                 index \u003d lookup.lastIndexOf(\"/\");\n                 lookup \u003d lookup.substring(0, index);\n             } else {\n                 // More ..\u0027s than dirs, return null\n                 return null;\n             }\n \n             index \u003d pth.indexOf(\"../\") + 3;\n             pth \u003d pth.substring(index);\n         }\n \n         return new StringBuffer(lookup).append(\"/\").append(pth).toString();\n     }\n\\ No newline at end of file\n",
      "extendedDetails": {}
    },
    "b901739a6779843da45a917a141cfd17114909de": {
      "type": "Ymovefromfile",
      "commitMessage": "moved all filename methods out of FileUtils and into the new FilenameUtils class. Updated the unit tests, though one test in FileUtilsTest does a bit of Filename testing. Javadoc will need a bit of checking. Updated tasks.xml to reflect this.\n\n\ngit-svn-id: https://svn.apache.org/repos/asf/jakarta/commons/proper/io/trunk@140425 13f79535-47bb-0310-9956-ffa450edef68\n",
      "commitDate": 1069620210000,
      "commitName": "b901739a6779843da45a917a141cfd17114909de",
      "commitAuthor": "Henri Yandell",
      "commitDateOld": 1069618450000,
      "commitNameOld": "f5e41b7cdb3aed5b19ad741cccb004dfeca745ac",
      "commitAuthorOld": "Henri Yandell",
      "daysBetweenCommits": 0.02,
      "commitsBetweenForRepo": 1,
      "commitsBetweenForFile": 1,
      "diff": "",
      "extendedDetails": {
        "oldPath": "src/java/org/apache/commons/io/FileUtils.java",
        "newPath": "src/java/org/apache/commons/io/FilenameUtils.java",
        "oldMethodName": "catPath",
        "newMethodName": "catPath"
      }
    },
    "8eeb52fc81c4e65c00839cfeef9f1cde8b1cc613": {
      "type": "Ymovefromfile",
      "commitMessage": "FileUtil moved into FileUtils. Oddly enough no methods clash in name.\nHowever there is a lot of clash of functionality, so methods need to be\nconsidered and removed.\n\n\ngit-svn-id: https://svn.apache.org/repos/asf/jakarta/commons/proper/io/trunk@140314 13f79535-47bb-0310-9956-ffa450edef68\n",
      "commitDate": 1027819689000,
      "commitName": "8eeb52fc81c4e65c00839cfeef9f1cde8b1cc613",
      "commitAuthor": "Henri Yandell",
      "commitDateOld": 1026599866000,
      "commitNameOld": "fcb1f1dc86e216faca4bdb9626200d99a6d9915a",
      "commitAuthorOld": "Nicola Ken Barozzi",
      "daysBetweenCommits": 14.12,
      "commitsBetweenForRepo": 1,
      "commitsBetweenForFile": 1,
      "diff": "",
      "extendedDetails": {
        "oldPath": "src/java/org/apache/commons/io/FileUtil.java",
        "newPath": "src/java/org/apache/commons/io/FileUtils.java",
        "oldMethodName": "catPath",
        "newMethodName": "catPath"
      }
    },
    "c360a10db25701f682849e5913d150f13a09f3bb": {
      "type": "Yintroduced",
      "commitMessage": "New io classes from Avalon excalibur.\n\n\ngit-svn-id: https://svn.apache.org/repos/asf/jakarta/commons/proper/io/trunk@140301 13f79535-47bb-0310-9956-ffa450edef68\n",
      "commitDate": 1026166486000,
      "commitName": "c360a10db25701f682849e5913d150f13a09f3bb",
      "commitAuthor": "Nicola Ken Barozzi"
    }
  }
}