{
  "origin": "codeshovel",
  "repositoryName": "checkstyle",
  "repositoryPath": "/home/ncbradley/codeshovel-repos/checkstyle/.git",
  "startCommitName": "119fd4fb33bef9f5c66fc950396669af842c21a3",
  "sourceFileName": "SimplifyBooleanReturnCheck.java",
  "functionName": "isBooleanLiteralType",
  "functionId": "isBooleanLiteralType___tokenType-int",
  "sourceFilePath": "src/main/java/com/puppycrawl/tools/checkstyle/checks/coding/SimplifyBooleanReturnCheck.java",
  "functionStartLine": 152,
  "functionEndLine": 156,
  "changeHistory": [
    "31f6765fdcf2233ca6c53730c2fc196576557f66",
    "1bd30555eac039d0486dffb3fc43b7a34117909b",
    "bb1b29851f14bf7eaf5656e01c285c0f5f3b9000",
    "f1efb27670a93690577f1bae17fc9dcbd88a795d",
    "9920857810ecc9efdbca19e2749b75abc0cbbf14",
    "e6571e6f5703fdd89bc6cbeddcce767e58ddbf50"
  ],
  "changeHistoryShort": {
    "31f6765fdcf2233ca6c53730c2fc196576557f66": "Ybodychange",
    "1bd30555eac039d0486dffb3fc43b7a34117909b": "Ybodychange",
    "bb1b29851f14bf7eaf5656e01c285c0f5f3b9000": "Ymultichange(Yparameterchange,Ybodychange)",
    "f1efb27670a93690577f1bae17fc9dcbd88a795d": "Yfilerename",
    "9920857810ecc9efdbca19e2749b75abc0cbbf14": "Yfilerename",
    "e6571e6f5703fdd89bc6cbeddcce767e58ddbf50": "Yintroduced"
  },
  "changeHistoryDetails": {
    "31f6765fdcf2233ca6c53730c2fc196576557f66": {
      "type": "Ybodychange",
      "commitMessage": "Issue #2080: Fix typos in code\n\nFixes some `SpellCheckingInspection` inspection violations.\n\nDescription:\n\u003eSpellchecker inspection helps locate typos and misspelling in your code, comments and literals.\n",
      "commitDate": 1441403297000,
      "commitName": "31f6765fdcf2233ca6c53730c2fc196576557f66",
      "commitAuthor": "Michal Kordas",
      "commitDateOld": 1441047087000,
      "commitNameOld": "c899af31c112c07ea1244f6bbe2c5c6c56818ae5",
      "commitAuthorOld": "Ruslan Diachenko",
      "daysBetweenCommits": 4.12,
      "commitsBetweenForRepo": 73,
      "commitsBetweenForFile": 1,
      "diff": "@@ -1,5 +1,5 @@\n     private static boolean isBooleanLiteralType(final int tokenType) {\n-        final boolean iastrue \u003d tokenType \u003d\u003d TokenTypes.LITERAL_TRUE;\n+        final boolean isTrue \u003d tokenType \u003d\u003d TokenTypes.LITERAL_TRUE;\n         final boolean isFalse \u003d tokenType \u003d\u003d TokenTypes.LITERAL_FALSE;\n-        return iastrue || isFalse;\n+        return isTrue || isFalse;\n     }\n\\ No newline at end of file\n"
    },
    "1bd30555eac039d0486dffb3fc43b7a34117909b": {
      "type": "Ybodychange",
      "commitMessage": "Remove useless parentheses to fix PMD violations, issue #744\n\nParentheses are considered unnecessary if the evaluation order of an expression remains unchanged if the parentheses are removed.\n",
      "commitDate": 1426023398000,
      "commitName": "1bd30555eac039d0486dffb3fc43b7a34117909b",
      "commitAuthor": "Michal Kordas",
      "commitDateOld": 1424437367000,
      "commitNameOld": "27149f3504a2f350b74f456a9bffbae76a460060",
      "commitAuthorOld": "alexkravin",
      "daysBetweenCommits": 18.36,
      "commitsBetweenForRepo": 91,
      "commitsBetweenForFile": 1,
      "diff": "@@ -1,6 +1,6 @@\n     private static boolean isBooleanLiteralType(final int tokenType)\n     {\n-        final boolean iastrue \u003d (tokenType \u003d\u003d TokenTypes.LITERAL_TRUE);\n-        final boolean isFalse \u003d (tokenType \u003d\u003d TokenTypes.LITERAL_FALSE);\n+        final boolean iastrue \u003d tokenType \u003d\u003d TokenTypes.LITERAL_TRUE;\n+        final boolean isFalse \u003d tokenType \u003d\u003d TokenTypes.LITERAL_FALSE;\n         return iastrue || isFalse;\n     }\n\\ No newline at end of file\n"
    },
    "bb1b29851f14bf7eaf5656e01c285c0f5f3b9000": {
      "type": "Ymultichange(Yparameterchange,Ybodychange)",
      "commitMessage": "Prefixes, coding, #512\n",
      "commitDate": 1421677214000,
      "commitName": "bb1b29851f14bf7eaf5656e01c285c0f5f3b9000",
      "commitAuthor": "alexkravin",
      "subchanges": [
        "Yparameterchange",
        "Ybodychange"
      ]
    },
    "f1efb27670a93690577f1bae17fc9dcbd88a795d": {
      "type": "Yfilerename",
      "commitMessage": "moving to standard directory layout\n",
      "commitDate": 1393953491000,
      "commitName": "f1efb27670a93690577f1bae17fc9dcbd88a795d",
      "commitAuthor": "Ivan Sopov",
      "commitDateOld": 1393482905000,
      "commitNameOld": "1cdaeaaa4fbf02a7388f1fcbea1c86ef0ea32fed",
      "commitAuthorOld": "Andrew Gaul",
      "daysBetweenCommits": 5.45,
      "commitsBetweenForRepo": 1,
      "commitsBetweenForFile": 1,
      "diff": ""
    },
    "9920857810ecc9efdbca19e2749b75abc0cbbf14": {
      "type": "Yfilerename",
      "commitMessage": "Refactored the Coding checks\n",
      "commitDate": 1055680780000,
      "commitName": "9920857810ecc9efdbca19e2749b75abc0cbbf14",
      "commitAuthor": "Oliver Burn",
      "commitDateOld": 1055612861000,
      "commitNameOld": "e464c231eccec72f964131d9aeb5e49982c4b3bb",
      "commitAuthorOld": "Oleg Sukhodolsky",
      "daysBetweenCommits": 0.79,
      "commitsBetweenForRepo": 1,
      "commitsBetweenForFile": 1,
      "diff": ""
    },
    "e6571e6f5703fdd89bc6cbeddcce767e58ddbf50": {
      "type": "Yintroduced",
      "commitMessage": "removed paranoia checks to increase code coverage\n",
      "commitDate": 1036696210000,
      "commitName": "e6571e6f5703fdd89bc6cbeddcce767e58ddbf50",
      "commitAuthor": "Lars Kühne"
    }
  }
}