{
  "origin": "codeshovel",
  "repositoryName": "guava",
  "repositoryPath": "/home/ncbradley/cs-repos/guava/.git",
  "startCommitName": "34c1616279efe08089960aafd3df486cf8a04820",
  "sourceFileName": "MapMakerInternalMap.java",
  "functionName": "getWeakValueReferenceForTesting",
  "functionId": "getWeakValueReferenceForTesting___e-InternalEntry__K,V,?__",
  "sourceFilePath": "android/guava/src/com/google/common/collect/MapMakerInternalMap.java",
  "functionStartLine": 2190,
  "functionEndLine": 2193,
  "changeHistory": [
    "86eabf1fe6991cf7fbc65980dac59a604303b362",
    "9b94fb3965c6869b0ac47420958a4bbae0b2d54c"
  ],
  "changeHistoryShort": {
    "86eabf1fe6991cf7fbc65980dac59a604303b362": "Ybodychange",
    "9b94fb3965c6869b0ac47420958a4bbae0b2d54c": "Yintroduced"
  },
  "changeHistoryDetails": {
    "86eabf1fe6991cf7fbc65980dac59a604303b362": {
      "type": "Ybodychange",
      "commitMessage": "Omit some unnecessary parens\n\nRELNOTES\u003dN/A\n\n-------------\nCreated by MOE: https://github.com/google/moe\nMOE_MIGRATED_REVID\u003d201703715\n",
      "commitDate": 1530203235000,
      "commitName": "86eabf1fe6991cf7fbc65980dac59a604303b362",
      "commitAuthor": "cushon",
      "commitDateOld": 1514488260000,
      "commitNameOld": "defe4e880cb9c6e8c949ad86ef5fb3ae86b433d0",
      "commitAuthorOld": "cnsun",
      "daysBetweenCommits": 181.89,
      "commitsBetweenForRepo": 189,
      "commitsBetweenForFile": 1,
      "diff": "@@ -1,4 +1,4 @@\n     public WeakValueReference\u003cK, V, WeakKeyWeakValueEntry\u003cK, V\u003e\u003e getWeakValueReferenceForTesting(\n         InternalEntry\u003cK, V, ?\u003e e) {\n-      return (castForTesting(e)).getValueReference();\n+      return castForTesting(e).getValueReference();\n     }\n\\ No newline at end of file\n"
    },
    "9b94fb3965c6869b0ac47420958a4bbae0b2d54c": {
      "type": "Yintroduced",
      "commitMessage": "Begin exporting sources of Guava for Android.\n\npom.xml files to come.\n\n-------------\nCreated by MOE: https://github.com/google/moe\nMOE_MIGRATED_REVID\u003d153757913\n",
      "commitDate": 1492741671000,
      "commitName": "9b94fb3965c6869b0ac47420958a4bbae0b2d54c",
      "commitAuthor": "zhenghua"
    }
  }
}